boolformer
