Metadata-Version: 2.1
Name: boolformer
Version: 0.1.9
Summary: Transformers for symbolic regression of Boolean functions
Author: Stéphane d'Ascoli
Author-email: stephane.dascoli@gmail.com
License: MIT
Classifier: Programming Language :: Python :: 3
Classifier: Intended Audience :: Science/Research
Classifier: License :: OSI Approved :: MIT License
Classifier: Topic :: Scientific/Engineering :: Artificial Intelligence
License-File: LICENSE
